LICENSE.txt
MANIFEST.in
README.md
setup.py
met/__init__.py
met/met.py
met.egg-info/PKG-INFO
met.egg-info/SOURCES.txt
met.egg-info/dependency_links.txt
met.egg-info/top_level.txt