Metadata-Version: 2.1
Name: met
Version: 1.0.1
Summary: Multinomial Exact Tests
Home-page: https://pypi/project/met/
Author: Dreas Nielsen
Author-email: dnielsen@integral-corp.com
License: GPL
Keywords: Statistics,Multnomial exact test,Multinomial
Platform: UNKNOWN
Classifier: Intended Audience :: End Users/Desktop
Classifier: Programming Language :: Python
Classifier: License :: OSI Approved :: GNU General Public License (GPL)
Classifier: Operating System :: OS Independent
Classifier: Topic :: Office/Business
Requires-Python: >=2.7
